spiderweb/__init__.py
spiderweb/constants.py
spiderweb/converters.py
spiderweb/db.py
spiderweb/decorators.py
spiderweb/default_views.py
spiderweb/example_validator.py
spiderweb/exceptions.py
spiderweb/files.py
spiderweb/jinja_core.py
spiderweb/jinja_extensions.py
spiderweb/local_server.py
spiderweb/main.py
spiderweb/request.py
spiderweb/response.py
spiderweb/routes.py
spiderweb/secrets.py
spiderweb/server_checks.py
spiderweb/utils.py
spiderweb/middleware/__init__.py
spiderweb/middleware/base.py
spiderweb/middleware/cors.py
spiderweb/middleware/csrf.py
spiderweb/middleware/gzip.py
spiderweb/middleware/pydantic.py
spiderweb/middleware/sessions.py
spiderweb/tests/__init__.py
spiderweb/tests/helpers.py
spiderweb/tests/middleware.py
spiderweb/tests/test.html
spiderweb/tests/test_cookies.py
spiderweb/tests/test_db.py
spiderweb/tests/test_exceptions.py
spiderweb/tests/test_files.py
spiderweb/tests/test_jinja_extras.py
spiderweb/tests/test_local_server.py
spiderweb/tests/test_middleware.py
spiderweb/tests/test_responses.py
spiderweb/tests/test_secrets.py
spiderweb/tests/test_server.py
spiderweb/tests/test_server_checks.py
spiderweb/tests/test_variable_urls.py
spiderweb/tests/views_for_tests.py
spiderweb/tests/staticfiles/.gitkeep
spiderweb/tests/staticfiles/file_for_testing_fileresponse.txt
spiderweb/tests/staticfiles/style.css
spiderweb_framework-2.2.1.dist-info/METADATA
spiderweb_framework-2.2.1.dist-info/WHEEL
spiderweb_framework-2.2.1.dist-info/licenses/LICENSE.txt
spiderweb_framework-2.2.1.dist-info/RECORD
