Metadata-Version: 2.4
Name: spiderweb-framework
Version: 2.2.1
Summary: A small web framework, just big enough for a spider.
Project-URL: Homepage, https://github.com/itsthejoker/spiderweb
Project-URL: Documentation, https://github.com/itsthejoker/spiderweb
Project-URL: Repository, https://git.joekaufeld.com/jkaufeld/spiderweb
Project-URL: Bug Tracker, https://github.com/itsthejoker/spiderweb/issues
Author-email: Joe Kaufeld <opensource@joekaufeld.com>
License-Expression: MIT
License-File: LICENSE.txt
Classifier: Development Status :: 4 - Beta
Classifier: Environment :: Web Environment
Classifier: Intended Audience :: Developers
Classifier: Programming Language :: Python :: 3 :: Only
Classifier: Programming Language :: Python :: 3.11
Classifier: Programming Language :: Python :: 3.12
Classifier: Programming Language :: Python :: 3.13
Classifier: Topic :: Internet :: WWW/HTTP :: HTTP Servers
Classifier: Topic :: Internet :: WWW/HTTP :: WSGI
Classifier: Topic :: Internet :: WWW/HTTP :: WSGI :: Application
Classifier: Topic :: Software Development :: Libraries :: Application Frameworks
Requires-Python: >=3.11
Requires-Dist: advanced-alchemy<2.0.0,>=1.6.3
Requires-Dist: cryptography>=46.0.2
Requires-Dist: email-validator>=2.3.0
Requires-Dist: jinja2>=3.1.6
Requires-Dist: multipart>=1.3.0
Requires-Dist: sqlalchemy>=2.0.44
Provides-Extra: pydantic
Requires-Dist: pydantic<3,>=2.8.2; extra == 'pydantic'
